CHANGELOG.txt
LICENSE
MANIFEST.in
README.md
pyproject.toml
requirements.txt
setup.py
test.py
facetranscript/__init__.py
facetranscript/capture_face.py
facetranscript/face_set.py
facetranscript/store_catured_image.py
facetranscript/user_database.py
facetranscript.egg-info/PKG-INFO
facetranscript.egg-info/SOURCES.txt
facetranscript.egg-info/dependency_links.txt
facetranscript.egg-info/requires.txt
facetranscript.egg-info/top_level.txt