Metadata-Version: 2.1
Name: facetranscript
Version: 0.0.3.1
Summary: To Capture user face and store it in database
Home-page: https://github.com/CrimsonDevil333333/FaceTranscript
Author: Satyaa Goyal
Author-email: satya.goyal333333@gmail.com
Keywords: facetranscript
Classifier: Development Status :: 3 - Alpha
Classifier: Intended Audience :: Developers
Classifier: Topic :: Software Development
Classifier: Operating System :: Microsoft :: Windows
Classifier: License :: OSI Approved :: MIT License
Classifier: Programming Language :: Python :: 3
License-File: LICENSE
